oauthenticator/__init__.py
oauthenticator/_version.py
oauthenticator/auth0.py
oauthenticator/azuread.py
oauthenticator/bitbucket.py
oauthenticator/cilogon.py
oauthenticator/common.py
oauthenticator/generic.py
oauthenticator/github.py
oauthenticator/gitlab.py
oauthenticator/globus.py
oauthenticator/google.py
oauthenticator/keycloak.py
oauthenticator/mediawiki.py
oauthenticator/oauth2.py
oauthenticator/okpy.py
oauthenticator/openshift.py
oauthenticatordev-0.7.4.dev0.dist-info/METADATA
oauthenticatordev-0.7.4.dev0.dist-info/RECORD
oauthenticatordev-0.7.4.dev0.dist-info/WHEEL
oauthenticatordev-0.7.4.dev0.dist-info/top_level.txt
